{"metadata":{"result_type":"recent","iso_language_code":"en"},"in_reply_to_status_id_str":"1101158420181331973","in_reply_to_status_id":1101158420181331973,"created_at":"Thu Feb 28 17:26:46 +0000 2019","in_reply_to_user_id_str":"855363234836230144","source":"<a href=\"http://twitter.com/download/android\" rel=\"nofollow\">Twitter for Android<\/a>","retweet_count":0,"retweeted":false,"geo":null,"in_reply_to_screen_name":"40commando","is_quote_status":false,"id_str":"1101171867086409734","in_reply_to_user_id":855363234836230144,"favorite_count":0,"id":1101171867086409734,"text":"Secretary of State @GavinWilliamson will be interviewed live on BBC tonight at 1830 to discuss the future of Norton\u2026 https://t.co/DXuXYn4Wgn","place":null,"lang":"en","favorited":false,"possibly_sensitive":false,"coordinates":null,"truncated":true,"entities":{"urls":[{"display_url":"twitter.com/i/web/status/1\u2026","indices":[117,140],"expanded_url":"https://twitter.com/i/web/status/1101171867086409734","url":"https://t.co/DXuXYn4Wgn"}],"hashtags":[],"user_mentions":[{"indices":[19,35],"screen_name":"GavinWilliamson","id_str":"368314502","name":"Gavin Williamson MP","id":368314502}],"symbols":[]},"contributors":null,"user":{"utc_offset":null,"friends_count":277,"profile_image_url_https":"https://pbs.twimg.com/profile_images/872173858094272515/RZPzxVDl_normal.jpg","listed_count":42,"profile_background_image_url":"http://abs.twimg.com/images/themes/theme1/bg.png","default_profile_image":false,"favourites_count":1033,"description":"Official Twitter account for 40 Commando Royal Marines. A highly trained Commando force, held at very high readiness by UK MOD for crisis response.","created_at":"Fri Apr 21 10:11:01 +0000 2017","is_translator":false,"profile_background_image_url_https":"https://abs.twimg.com/images/themes/theme1/bg.png","protected":false,"screen_name":"40commando","id_str":"855363234836230144","profile_link_color":"004712","is_translation_enabled":false,"translator_type":"none","id":855363234836230144,"geo_enabled":true,"profile_background_color":"000000","lang":"en","has_extended_profile":true,"profile_sidebar_border_color":"000000","profile_text_color":"000000","verified":false,"profile_image_url":"http://pbs.twimg.com/profile_images/872173858094272515/RZPzxVDl_normal.jpg","time_zone":null,"url":"https://t.co/ZtA9IR69QJ","contributors_enabled":false,"profile_background_tile":false,"profile_banner_url":"https://pbs.twimg.com/profile_banners/855363234836230144/1548018873","entities":{"description":{"urls":[]},"url":{"urls":[{"display_url":"royalnavy.mod.uk/40Cdo","indices":[0,23],"expanded_url":"http://www.royalnavy.mod.uk/40Cdo","url":"https://t.co/ZtA9IR69QJ"}]}},"statuses_count":798,"follow_request_sent":false,"followers_count":7654,"profile_use_background_image":false,"default_profile":false,"following":false,"name":"40 Commando Royal Marines","location":"Norway","profile_sidebar_fill_color":"000000","notifications":false}}